{
  "projects": [
    {
      "slug": "el-nido",
      "title": "El Nido",
      "m2": 327,
      "status": "Proyecto",
      "year": 2026,
      "location": "El Nido, Manantiales, San Carlos, Uruguay",
      "credits": {
        "proyecto": "Noreste Arquitectura",
        "equipo": "Catalina Andersch",
        "obra": null,
        "paisajismo": null,
        "interiorismo": null,
        "instalaciones": null,
        "estructura": null,
        "fotografias": null
      },
      "exteriorImages": ["01.jpg","02.jpg","03.jpg","04.jpg","05.jpg","06.jpg","07.jpg"],
      "interiorImages": ["01.jpg","02.jpg","03.jpg","04.jpg","05.jpg","06.jpg","07.jpg","08.jpg"]
    },

    {
      "slug": "club-buchardo-nuñez",
      "title": "Club Náutico Buchardo Núñez",
      "m2": 12000,
      "status": "Proyecto",
      "year": 2025,
      "location": "Nuñez, Ciudad de Buenos Aires, Argentina",
      "credits": {
        "proyecto": "Noreste Arquitectura",
        "equipo": "Catalina Andersch",
        "obra": null,
        "paisajismo": null,
        "interiorismo": null,
        "instalaciones": null,
        "estructura": null,
        "fotografias": null
      },
      "exteriorImages": ["01.jpg","02.jpg","03.jpg","04.jpg","05.jpg","06.jpg","07.jpg","08.jpg","09.jpg","10.jpg"],
      "interiorImages": ["01.jpg","02.jpg","03.jpg"]
    },

    {
      "slug": "triunvirato",
      "title": "Casa en Villa Urquiza",
      "m2": 140,
      "status": "Construido",
      "year": 2025,
      "location": "Villa Urquiza, Ciudad de Buenos Aires, Argentina",
      "credits": {
        "proyecto": "Noreste Arquitectura",
        "equipo": "Catalina Andersch",
        "obra": "Noreste Arquitectura",
        "paisajismo": null,
        "interiorismo": null,
        "instalaciones": null,
        "estructura": null,
        "fotografias": null
      },
      "exteriorImages": ["01.jpg","02.jpg","03.jpg","04.jpg","05.jpg","06.jpg","07.jpg"],
      "interiorImages": ["01.jpg","02.jpg","03.jpg","04.jpg","05.jpg","06.jpg","07.jpg","08.jpg"]
    },

    {
      "slug": "vidt",
      "title": "Vidt",
      "m2": 29,
      "status": "Proyecto",
      "year": 2025,
      "location": "Recoleta, Ciudad de Buenos Aires, Argentina",
      "credits": {
        "proyecto": "Noreste Arquitectura",
        "equipo": null,
        "obra": null,
        "paisajismo": null,
        "interiorismo": null,
        "instalaciones": null,
        "estructura": null,
        "fotografias": null
      },
      "exteriorImages": [],
      "interiorImages": ["01.jpg","02.jpg","03.jpg","04.jpg"]
    },

    {
      "slug": "vivienda-la-tacuara",
      "title": "La Tacuara",
      "m2": 190,
      "status": "En obra",
      "year": 2026,
      "location": "Cañuelas, Provincia de Buenos Aires, Argentina",
      "credits": {
        "proyecto": "Noreste Arquitectura",
        "equipo": "Catalina Andersch",
        "obra": "Noreste Arquitectura",
        "paisajismo": "Noreste Arquitectura",
        "interiorismo": "Noreste Arquitectura",
        "instalaciones": "Noreste Arquitectura",
        "estructura": "Ing. Claudio Lara",
        "fotografias": null
      },
      "exteriorImages": ["01.jpg","02.jpg","03.jpg"],
      "interiorImages": ["01.jpg","02.jpg","03.jpg","04.jpg","05.jpg","06.jpg","07.jpg","08.jpg","09.jpg","10.jpg"]
    },

    {
      "slug": "casa-belen-maria",
      "title": "Casa Belén María",
      "m2": 160,
      "status": "En obra",
      "year": 2026,
      "location": "Coronel Suárez, Sur de la Provincia de Buenos Aires, Argentina",
      "credits": {
        "proyecto": "Noreste Arquitectura",
        "equipo": "Catalina Andersch",
        "obra": "Noreste Arquitectura",
        "paisajismo": "Noreste Arquitectura",
        "interiorismo": "Noreste Arquitectura",
        "instalaciones": "Noreste Arquitectura",
        "estructura": "Noreste Arquitectura",
        "fotografias": null
      },
      "exteriorImages": ["01.jpg","02.jpg","03.jpg","04.jpg"],
      "interiorImages": ["01.jpg","02.jpg","03.jpg","04.jpg","05.jpg","06.jpg"]
    },

    {
      "slug": "modulo-ff",
      "title": "La Tacuara 02",
      "m2": 120,
      "status": "En obra",
      "year": 2026,
      "location": "Cañuelas, Provincia de Buenos Aires, Argentina",
      "credits": {
        "proyecto": "Josefina Gardey + Noreste Arquitectura",
        "equipo": null,
        "obra": "Noreste Arquitectura",
        "paisajismo": "Noreste Arquitectura",
        "interiorismo": "Noreste Arquitectura",
        "instalaciones": "Noreste Arquitectura",
        "estructura": "Noreste Arquitectura",
        "fotografias": null
      },
      "exteriorImages": ["01.jpg","02.jpg","03.jpg","04.jpg","05.jpg","06.jpg"],
      "interiorImages": ["01.jpg","02.jpg","03.jpg","04.jpg","05.jpg","06.jpg","07.jpg","08.jpg","09.jpg"]
    },

    {
      "slug": "hipico-la-leyenda",
      "title": "Hípico La Leyenda",
      "m2": 120000,
      "status": "En obra",
      "year": 2026,
      "location": "Pilar, Provincia de Buenos Aires, Argentina",
      "credits": {
        "proyecto": "Noreste Arquitectura",
        "equipo": null,
        "obra": null,
        "paisajismo": null,
        "interiorismo": null,
        "instalaciones": null,
        "estructura": null,
        "fotografias": null
      },
      "exteriorImages": ["01.jpg","02.jpg","03.jpg","04.jpg","05.jpg","06.jpg","07.jpg","08.jpg","09.jpg","10.jpg","11.jpg","12.jpg","13.jpg","14.jpg","15.jpg","16.jpg","17.jpg","18.jpg","19.jpg","20.jpg"],
      "interiorImages": ["01.jpg","02.jpg","03.jpg","04.jpg","05.jpg","06.jpg","07.jpg","08.jpg","09.jpg","10.jpg"]
    },

    {
      "slug": "el-metejon",
      "title": "Sector Ecuestre El Metejón",
      "m2": 4000,
      "status": "En obra",
      "year": 2025,
      "location": "Alejandro Petión, Provincia de Buenos Aires, Argentina",
      "credits": {
        "proyecto": "Noreste Arquitectura",
        "equipo": "Catalina Andersch",
        "obra": null,
        "paisajismo": null,
        "interiorismo": null,
        "instalaciones": null,
        "estructura": null,
        "fotografias": null
      },
      "exteriorImages": ["01.jpg","02.jpg","03.jpg","04.jpg","05.jpg","06.jpg","07.jpg"],
      "interiorImages": ["01.jpg","02.jpg"]
    },

    {
      "slug": "caballerizas",
      "title": "Caballerizas",
      "m2": 2800,
      "status": "Construido",
      "year": 2025,
      "location": "La Dolfina Polo Club, Provincia de Buenos Aires, Argentina",
      "credits": {
        "proyecto": "Josefina Gardey + Noreste Arquitectura",
        "equipo": null,
        "obra": null,
        "paisajismo": null,
        "interiorismo": null,
        "instalaciones": null,
        "estructura": null,
        "fotografias": null
      },
      "exteriorImages": ["01.jpg","02.jpg","03.jpg","04.jpg","05.jpg","06.jpg","07.jpg","08.jpg","09.jpg","10.jpg","11.jpg","12.jpg","13.jpg","14.jpg","15.jpg","16.jpg","17.jpg","18.jpg","19.jpg","20.jpg"],
      "interiorImages": ["01.jpg","02.jpg","03.jpg","04.jpg","05.jpg","06.jpg","07.jpg","08.jpg","09.jpg","10.jpg"]
    },

    {
      "slug": "reforma-vedia",
      "title": "Vedia",
      "m2": 70,
      "status": "Construido",
      "year": 2024,
      "location": "Saavedra, Ciudad de Buenos Aires, Argentina",
      "credits": {
        "proyecto": "Noreste Arquitectura",
        "equipo": null,
        "obra": "Noreste Arquitectura",
        "paisajismo": null,
        "interiorismo": null,
        "instalaciones": null,
        "estructura": null,
        "fotografias": null
      },
      "exteriorImages": ["01.jpg"],
      "interiorImages": ["01.jpg","02.jpg","03.jpg"]
    },

    {
      "slug": "caballerizas-poroto",
      "title": "Caballerizas La Dolfina",
      "m2": 140,
      "status": "Construido",
      "year": 2025,
      "location": "La Dolfina Polo Club, Provincia de Buenos Aires, Argentina",
      "credits": {
        "proyecto": "Noreste Arquitectura",
        "equipo": "Catalina Andersch",
        "obra": "Noreste Arquitectura",
        "paisajismo": null,
        "interiorismo": "Noreste Arquitectura",
        "instalaciones": null,
        "estructura": null,
        "fotografias": null
      },
      "exteriorImages": ["01.jpg","02.jpg"],
      "interiorImages": ["01.jpg","02.jpg","03.jpg","04.jpg","05.jpg","06.jpg"]
    },

    {
      "slug": "la-martona",
      "title": "La Martona",
      "m2": 200,
      "status": "Construido",
      "year": 2025,
      "location": "Cañuelas, Provincia de Buenos Aires, Argentina",
      "credits": {
        "proyecto": "Noreste Arquitectura",
        "equipo": "Catalina Andersch",
        "obra": "Noreste Arquitectura",
        "paisajismo": null,
        "interiorismo": "Noreste Arquitectura",
        "instalaciones": null,
        "estructura": null,
        "fotografias": null
      },
      "exteriorImages": ["01.jpg","02.jpg","03.jpg","04.jpg","05.jpg","06.jpg","07.jpg","08.jpg","09.jpg","10.jpg"],
      "interiorImages": ["01.jpg","02.jpg","03.jpg","04.jpg","05.jpg","06.jpg","07.jpg","08.jpg","09.jpg","10.jpg"]
    },

    {
      "slug": "puesto-el-mate",
      "title": "El Mate",
      "m2": 112,
      "status": "Construido",
      "year": 2024,
      "location": "San Antonio de Areco, Provincia de Buenos Aires, Argentina",
      "credits": {
        "proyecto": "Noreste Arquitectura",
        "equipo": null,
        "obra": null,
        "paisajismo": null,
        "interiorismo": null,
        "instalaciones": null,
        "estructura": null,
        "fotografias": null
      },
      "exteriorImages": ["01.jpg","02.jpg","03.jpg","04.jpg","05.jpg","06.jpg"],
      "interiorImages": []
    },

    {
      "slug": "casa-mia",
      "title": "La Martona 02",
      "m2": 140,
      "status": "Construido",
      "year": 2025,
      "location": "Cañuelas, Provincia de Buenos Aires, Argentina",
      "credits": {
        "proyecto": "Josefina Gardey + Noreste Arquitectura",
        "equipo": null,
        "obra": null,
        "paisajismo": null,
        "interiorismo": null,
        "instalaciones": null,
        "estructura": null,
        "fotografias": null
      },
      "exteriorImages": ["01.jpg","02.jpg","03.jpg","04.jpg","05.jpg","06.jpg"],
      "interiorImages": ["01.jpg","02.jpg","03.jpg","04.jpg","05.jpg","06.jpg","07.jpg","08.jpg","09.jpg"]
    }

  ]
}
